setup.py
plex/__init__.py
plex/client.py
plex/episode.py
plex/library.py
plex/media.py
plex/movie.py
plex/season.py
plex/section.py
plex/server.py
plex/show.py
plex/test.py
plex/video.py
py_plex.egg-info/PKG-INFO
py_plex.egg-info/SOURCES.txt
py_plex.egg-info/dependency_links.txt
py_plex.egg-info/top_level.txt