Metadata-Version: 1.1
Name: py-plex
Version: 0.0.1
Summary: Python client library for Plex Media Server
Home-page: https://github.com/rueckstiess/py-plex
Author: Thomas Rückstieß
Author-email: UNKNOWN
License: UNKNOWN
Platform: UNKNOWN
Classifier: Development Status :: 3 - Alpha
